pip_wrapper.py
skip_pip-0.1.2.dist-info/METADATA
skip_pip-0.1.2.dist-info/WHEEL
skip_pip-0.1.2.dist-info/entry_points.txt
skip_pip-0.1.2.dist-info/top_level.txt
skip_pip-0.1.2.dist-info/RECORD
