Metadata-Version: 2.2
Name: skip-pip
Version: 0.1.2
Summary: A pip wrapper that installs packages from requirements files while skipping packages that fail.
Home-page: https://github.com/saiadupa/skip-pip
Author: Your Name
Author-email: adupanithinsai@gmail.com
Classifier: Programming Language :: Python :: 3
Classifier: License :: OSI Approved :: MIT License
Dynamic: author
Dynamic: author-email
Dynamic: classifier
Dynamic: description
Dynamic: description-content-type
Dynamic: home-page
Dynamic: summary
